telepy_notify/__init__.py
telepy_notify/settings.json
telepy_notify/update_dependencies
telepy_notify/__dependencies__/__init__.py
telepy_notify/__dependencies__/__sources__/blissful_basics/.gitignore
telepy_notify/__dependencies__/__sources__/blissful_basics/.gitrepo
telepy_notify/__dependencies__/__sources__/blissful_basics/README.md
telepy_notify/__dependencies__/__sources__/blissful_basics/poetry.lock
telepy_notify/__dependencies__/__sources__/blissful_basics/pyproject.toml
telepy_notify/__dependencies__/__sources__/blissful_basics/main/license.txt
telepy_notify/__dependencies__/__sources__/blissful_basics/main/setup.py
telepy_notify/__dependencies__/__sources__/blissful_basics/main/blissful_basics/__init__.py
telepy_notify/__dependencies__/__sources__/blissful_basics/main/blissful_basics/settings.json
telepy_notify/__dependencies__/__sources__/blissful_basics/main/blissful_basics/update_dependencies
telepy_notify/__dependencies__/__sources__/blissful_basics/main/blissful_basics/__dependencies__/__init__.py
telepy_notify/__dependencies__/__sources__/blissful_basics/main/blissful_basics/__dependencies__/__sources__/file_system_py/.gitignore
telepy_notify/__dependencies__/__sources__/blissful_basics/main/blissful_basics/__dependencies__/__sources__/file_system_py/.gitrepo
telepy_notify/__dependencies__/__sources__/blissful_basics/main/blissful_basics/__dependencies__/__sources__/file_system_py/README.md
telepy_notify/__dependencies__/__sources__/blissful_basics/main/blissful_basics/__dependencies__/__sources__/file_system_py/poetry.lock
telepy_notify/__dependencies__/__sources__/blissful_basics/main/blissful_basics/__dependencies__/__sources__/file_system_py/pyproject.toml
telepy_notify/__dependencies__/__sources__/blissful_basics/main/blissful_basics/__dependencies__/__sources__/file_system_py/logs/main.py.log
telepy_notify/__dependencies__/__sources__/blissful_basics/main/blissful_basics/__dependencies__/__sources__/file_system_py/main/license.txt
telepy_notify-0.2.1.dist-info/METADATA
telepy_notify-0.2.1.dist-info/WHEEL
telepy_notify-0.2.1.dist-info/top_level.txt
telepy_notify-0.2.1.dist-info/RECORD
