Metadata-Version: 2.1
Name: telepy-notify
Version: 0.2.1
Summary: Send telegram notifications
Home-page: https://github.com/jeff-hykin/telepy_notify
Author: Jeff Hykin
Author-email: jeff.hykin@gmail.com
License: MIT
Platform: UNKNOWN
Requires-Python: >=3.6
